{
    "Station Name": "oakisland_west",
    "Input File": "C:/Users/longjw/OneDrive - UNC-Wilmington/projects/WebCOOS/corey/for_Axiom_June3_2025/timex.oakisland_west-2025-06-06-132221Z.jpg",
    "Image Resize": "30",
    "Orientation": 2,
    "Transect Horizon Angle": 8.0,
    "Transect Spacing": 5.0,
    "Shoreline Transects": {
        "x": [
            [
                7.28374296065519,
                545.6333539440886
            ],
            [
                6.395277711407212,
                543.7499711401675
            ],
            [
                5.506812462159229,
                541.8665883362464
            ],
            [
                17.0063578155377,
                539.9832055323253
            ],
            [
                33.73470987847058,
                538.0998227284042
            ],
            [
                50.46306194140339,
                536.2164399244831
            ],
            [
                69.48881748379445,
                534.333057120562
            ],
            [
                88.81710441160637,
                532.4496743166408
            ],
            [
                108.14539133941814,
                530.6498437699689
            ],
            [
                127.47367826723007,
                528.9075124991224
            ],
            [
                149.72452615379478,
                527.1651812282759
            ],
            [
                178.24473709519734,
                525.4228499574293
            ],
            [
                206.76494803659995,
                523.6805186865829
            ],
            [
                235.9404750478257,
                521.9381874157364
            ],
            [
                265.20391214259894,
                520.1958561448898
            ],
            [
                7.28374296065519,
                545.6333539440886
            ],
            [
                8.172208209903166,
                547.5167367480097
            ],
            [
                9.060673459151149,
                549.4001195519309
            ],
            [
                9.949138708399126,
                551.283502355852
            ],
            [
                10.837603957647108,
                553.1668851597731
            ],
            [
                11.726069206895085,
                555.0502679636942
            ],
            [
                12.614534456143064,
                556.9336507676153
            ],
            [
                13.50299970539104,
                558.8170335715364
            ],
            [
                26.148072761911152,
                560.7024787162409
            ],
            [
                46.874771142938634,
                562.5921549987864
            ],
            [
                67.6014695239661,
                309.0862842286251
            ]
        ],
        "y": [
            [
                187.877627061814,
                263.53773075113344
            ],
            [
                182.70362355148754,
                258.2239006972132
            ],
            [
                177.52962004116102,
                252.9100706432928
            ],
            [
                174.09663788122978,
                247.59624058937254
            ],
            [
                171.39851658075673,
                242.28241053545227
            ],
            [
                168.7003952802837,
                236.96858048153197
            ],
            [
                166.3251529824619,
                231.65475042761165
            ],
            [
                163.9924286980708,
                226.34092037369135
            ],
            [
                161.65970441367972,
                221.03883282374613
            ],
            [
                159.32698012928861,
                215.74482627002018
            ],
            [
                157.40499500150926,
                210.45081971629426
            ],
            [
                156.36411139050918,
                205.15681316256834
            ],
            [
                155.3232277795091,
                199.8628066088424
            ],
            [
                154.37444283595582,
                194.56880005511644
            ],
            [
                153.43801284892308,
                189.2747935013905
            ],
            [
                187.877627061814,
                263.53773075113344
            ],
            [
                193.05163057214045,
                268.85156080505374
            ],
            [
                198.22563408246694,
                274.16539085897404
            ],
            [
                203.3996375927934,
                279.4792209128943
            ],
            [
                208.57364110311988,
                284.79305096681463
            ],
            [
                213.74764461344634,
                290.10688102073493
            ],
            [
                218.9216481237728,
                295.42071107465523
            ],
            [
                224.09565163409926,
                300.7345411285755
            ],
            [
                230.92193861892844,
                306.04866102559095
            ],
            [
                238.88402397261584,
                311.3633755702503
            ],
            [
                246.84610932630324,
                280.7845867528483
            ]
        ]
    },
    "Dune Line Info": {
        "Dune Line Points": [
            [
                474.37210584343984,
                156.21444321940464
            ],
            [
                466.7646085997794,
                160.77894156560092
            ],
            [
                461.1857772877619,
                172.95093715545755
            ],
            [
                456.11411245865486,
                189.68743109151052
            ],
            [
                459.66427783902975,
                214.53858875413454
            ],
            [
                472.8506063947078,
                239.89691289966927
            ],
            [
                487.5584343991179,
                269.31256890848954
            ],
            [
                505.8164277839029,
                296.69955898566707
            ],
            [
                522.0457552370451,
                322.05788313120183
            ]
        ]
    },
    "roi_points": [
        [
            5.243109151047435,
            175.99393605292175
        ],
        [
            52.40959206174202,
            168.38643880926134
        ],
        [
            140.65656008820287,
            157.73594266813672
        ],
        [
            210.138368246968,
            155.20011025358326
        ],
        [
            273.5341786108048,
            153.1714443219405
        ],
        [
            329.82965821389195,
            153.1714443219405
        ],
        [
            389.67530319735386,
            154.18577728776188
        ],
        [
            440.899117971334,
            155.70727673649395
        ],
        [
            484.008269018743,
            160.27177508269023
        ],
        [
            484.008269018743,
            179.0369349503859
        ],
        [
            518.4955898566703,
            184.10859977949286
        ],
        [
            531.6819184123484,
            224.17475192943775
        ],
        [
            560.0832414553472,
            304.3070562293275
        ],
        [
            568.1979051819184,
            327.12954796030874
        ],
        [
            310.5573318632855,
            279.45589856670347
        ],
        [
            263.39084895259094,
            322.05788313120183
        ],
        [
            13.864939360529235,
            226.2034178610805
        ]
    ],
    "image_size": [
        460,
        614
    ]
}
